LICENSE
README.md
setup.py
pywifiscan/__init__.py
pywifiscan/pywifiscan.py
pywifiscan.egg-info/PKG-INFO
pywifiscan.egg-info/SOURCES.txt
pywifiscan.egg-info/dependency_links.txt
pywifiscan.egg-info/top_level.txt
tests/__init__.py
tests/test_pywifiscan.py