Metadata-Version: 2.1
Name: pywifiscan
Version: 1.0.0
Summary: Library to get the received signal strength indicator (RSSI) from Wi-Fi networks.
Home-page: https://github.com/ferreirad08/pywifiscan
Author: David Ferreira
Author-email: ferreirad08@gmail.com
License: MIT
Project-URL: Source, https://github.com/ferreirad08/pywifiscan
Platform: UNKNOWN
Classifier: Programming Language :: Python :: 2.7
Classifier: Programming Language :: Python :: 3.6
Classifier: Programming Language :: Python :: 3.7
Classifier: Programming Language :: Python :: 3.8
Classifier: Programming Language :: Python :: 3.9
Classifier: Programming Language :: Python :: 3.10
Classifier: Programming Language :: Python :: 3.11
Classifier: License :: OSI Approved :: MIT License
Classifier: Operating System :: OS Independent
Requires-Python: >=2.7
License-File: LICENSE
